hks_pynetwork/__init__.py
hks_pynetwork/external.py
hks_pynetwork/internal.py
hks_pynetwork/packet.py
hks_pynetwork/packet_buffer.py
hks_pynetwork/secure_packet.py
hks_pynetwork/version.py
hks_pynetwork/errors/__init__.py
hks_pynetwork/errors/external.py
hks_pynetwork/errors/internal.py
hks_pynetwork/errors/packet.py
hks_pynetwork/errors/secure_packet.py
hks_pynetwork-0.0.5.dist-info/LICENSE
hks_pynetwork-0.0.5.dist-info/METADATA
hks_pynetwork-0.0.5.dist-info/WHEEL
hks_pynetwork-0.0.5.dist-info/top_level.txt
hks_pynetwork-0.0.5.dist-info/RECORD
