Metadata-Version: 2.1
Name: hks-pynetwork
Version: 0.0.5
Summary: A Python library is built to communicate between objects in internal or external programs.
Home-page: https://github.com/huykingsofm/hks_pynetwork
Author: huykingsofm
Author-email: huykingsofm@gmail.com
License: UNKNOWN
Project-URL: Bug Tracker, https://github.com/huykingsofm/hks_pynetwork/issues
Platform: UNKNOWN
Classifier: Programming Language :: Python :: 3
Classifier: License :: OSI Approved :: MIT License
Classifier: Operating System :: OS Independent
Requires-Python: >=3.7.1
Requires-Dist: hks-pylib (>=0.0.6)
Requires-Dist: hkserror (>=0.0.1)
